nandhana_ai/__init__.py
nandhana_ai/core.py
nandhana_ai-0.0.1.dist-info/METADATA
nandhana_ai-0.0.1.dist-info/WHEEL
nandhana_ai-0.0.1.dist-info/top_level.txt
nandhana_ai-0.0.1.dist-info/RECORD
