Metadata-Version: 2.4
Name: nandhana_ai
Version: 0.0.1
Summary: A Python library to interact with AI tools for responses and text summarization
Home-page: https://github.com/yourusername/nandhana_ai
Author: Nandhana C S
Requires-Python: >=3.8
Requires-Dist: openai
Dynamic: author
Dynamic: home-page
Dynamic: requires-dist
Dynamic: requires-python
Dynamic: summary
